{
	"backtrace" : 4,
	"backtraceGraph" : 
	{
		"commands" : 
		[
			"add_custom_target",
			"include",
			"generate_messages",
			"add_dependencies"
		],
		"files" : 
		[
			"cmake-build-debug/Lego-LOAM-master/cloud_msgs/cmake/cloud_msgs-genmsg.cmake",
			"/opt/ros/noetic/share/genmsg/cmake/genmsg-extras.cmake",
			"Lego-LOAM-master/cloud_msgs/CMakeLists.txt"
		],
		"nodes" : 
		[
			{
				"file" : 2
			},
			{
				"command" : 2,
				"file" : 2,
				"line" : 18,
				"parent" : 0
			},
			{
				"command" : 1,
				"file" : 1,
				"line" : 307,
				"parent" : 1
			},
			{
				"file" : 0,
				"parent" : 2
			},
			{
				"command" : 0,
				"file" : 0,
				"line" : 56,
				"parent" : 3
			},
			{
				"command" : 3,
				"file" : 0,
				"line" : 57,
				"parent" : 3
			}
		]
	},
	"dependencies" : 
	[
		{
			"backtrace" : 5,
			"id" : "cloud_msgs_generate_messages_cpp::@b6d9e42bdb94f1e16a6e"
		}
	],
	"id" : "cloud_msgs_gencpp::@b6d9e42bdb94f1e16a6e",
	"name" : "cloud_msgs_gencpp",
	"paths" : 
	{
		"build" : "Lego-LOAM-master/cloud_msgs",
		"source" : "Lego-LOAM-master/cloud_msgs"
	},
	"sources" : [],
	"type" : "UTILITY"
}
